slack_responder.py
slack_responder-1.1.0.dist-info/DESCRIPTION.rst
slack_responder-1.1.0.dist-info/METADATA
slack_responder-1.1.0.dist-info/RECORD
slack_responder-1.1.0.dist-info/WHEEL
slack_responder-1.1.0.dist-info/entry_points.txt
slack_responder-1.1.0.dist-info/metadata.json
slack_responder-1.1.0.dist-info/top_level.txt
