Metadata-Version: 2.0
Name: slack-responder
Version: 1.1.0
Summary: A slack bot that responds to regex patterns
Home-page: https://github.com/jarshwah/slack-pattern-responder
Author: Josh Smeaton
Author-email: josh.smeaton@gmail.com
License: MIT
Platform: unix
Platform: linux
Platform: osx
Classifier: Development Status :: 3 - Alpha
Classifier: License :: OSI Approved :: MIT License
Classifier: Intended Audience :: Developers
Classifier: Intended Audience :: Information Technology
Classifier: Intended Audience :: System Administrators
Classifier: Programming Language :: Python
Classifier: Programming Language :: Python :: 2.7
Classifier: Programming Language :: Python :: 3.4
Classifier: Programming Language :: Python :: 3.5
Requires-Dist: click
Requires-Dist: pyyaml
Requires-Dist: slackclient (>=1.0.5)
